collectionmodeladmin/__init__.py
collectionmodeladmin/base.py
collectionmodeladmin/forms.py
collectionmodeladmin/permissions.py
collectionmodeladmin/__pycache__/__init__.cpython-36.pyc
collectionmodeladmin/__pycache__/base.cpython-36.pyc
collectionmodeladmin/__pycache__/permissions.cpython-36.pyc
collectionmodeladmin/templates/collectionmodeladmin/index.html
collectionmodeladmin/templates/collectionmodeladmin/permissions/includes/collectionmodel_permissions_formset.html
collectionmodeladmin/templatetags/__init__.py
collectionmodeladmin/templatetags/collectionmodeladmin_tags.py
wagtail_collectionmodeladmin-0.1.4.dist-info/LICENSE
wagtail_collectionmodeladmin-0.1.4.dist-info/METADATA
wagtail_collectionmodeladmin-0.1.4.dist-info/WHEEL
wagtail_collectionmodeladmin-0.1.4.dist-info/top_level.txt
wagtail_collectionmodeladmin-0.1.4.dist-info/RECORD
