Metadata-Version: 2.1
Name: wagtail-collectionmodeladmin
Version: 0.1.4
Summary: Model Admin extension that utilizes the Wagtail collections
Home-page: https://github.com/BabisK/wagtail-collectionmodeladmin
Author: Babis Kaidos
Author-email: ckaidos@intracom-telecom.com
License: BSD
Platform: UNKNOWN
Classifier: Programming Language :: Python :: 3
Classifier: License :: OSI Approved :: BSD License
Classifier: Operating System :: OS Independent
Classifier: Development Status :: 3 - Alpha
Classifier: Framework :: Wagtail :: 2
Requires-Dist: wagtail (>=2.6)
